jmc/__init__.py
jmc/argument.py
jmc/block.py
jmc/enums.py
jmc/headers.py
jmc/module.py
jmc/template.py
test/test_count.py
test/test_echo.py
justmc_py-0.0.1.dist-info/LICENSE
justmc_py-0.0.1.dist-info/METADATA
justmc_py-0.0.1.dist-info/WHEEL
justmc_py-0.0.1.dist-info/top_level.txt
justmc_py-0.0.1.dist-info/RECORD
