Metadata-Version: 2.2
Name: JustMC.py
Version: 0.0.1
Summary: JustMC templating library in Python.
Author: HellishBro
License: MIT License
Project-URL: Homepage, https://github.com/HellishBro/JustMC.py
Project-URL: Issues, https://github.com/HellishBro/JustMC.py/issues
Keywords: JustMC
Classifier: Programming Language :: Python :: 3.12
Classifier: License :: OSI Approved :: MIT License
Classifier: Operating System :: OS Independent
Requires-Python: >=3.12
License-File: LICENSE
Requires-Dist: amulet-nbt
Requires-Dist: requests
Requires-Dist: setuptools
